dashiqlib/__init__.py
dashiqlib/chat.py
dashiqlib/clerk.py
dashiqlib/mongo.py
dashiqlib/util.py
dashiqlib-0.0.8.dist-info/METADATA
dashiqlib-0.0.8.dist-info/WHEEL
dashiqlib-0.0.8.dist-info/RECORD
